chanfig/__init__.py
chanfig/_version.py
chanfig/base.py
chanfig/config.py
chanfig/configclasses.py
chanfig/default_dict.py
chanfig/flat_dict.py
chanfig/nested_dict.py
chanfig/parser.py
chanfig/py.typed
chanfig/registry.py
chanfig/variable.py
chanfig/utils/__init__.py
chanfig/utils/annotation.py
chanfig/utils/functional.py
chanfig/utils/io.py
chanfig/utils/null.py
chanfig/utils/placeholder.py
chanfig/utils/safe_eval.py
chanfig-0.0.114.dist-info/licenses/LICENSE
chanfig-0.0.114.dist-info/licenses/LICENSE.header
chanfig-0.0.114.dist-info/METADATA
chanfig-0.0.114.dist-info/WHEEL
chanfig-0.0.114.dist-info/top_level.txt
chanfig-0.0.114.dist-info/RECORD
