Metadata-Version: 2.4
Name: chanfig
Version: 0.0.114
Summary: Easier Configuration
Author-email: Zhiyuan Chen <this@zyc.ai>, "Evian C. Liu" <evian.liu@outlook.com>
Maintainer-email: Zhiyuan Chen <this@zyc.ai>
License: Unlicense OR AGPL-3.0-or-later OR GPL-2.0-or-later OR BSD-4-Clause OR MIT OR Apache-2.0
Project-URL: documentation, https://chanfig.danling.org
Project-URL: homepage, https://chanfig.danling.org
Project-URL: repository, https://github.com/ZhiyuanChen/CHANfiG
Keywords: config,deep-learning,dict,machine-learning
Classifier: Development Status :: 5 - Production/Stable
Classifier: Intended Audience :: Developers
Classifier: Intended Audience :: Education
Classifier: Intended Audience :: Science/Research
Classifier: Operating System :: OS Independent
Classifier: Programming Language :: Python :: 3 :: Only
Classifier: Programming Language :: Python :: 3.8
Classifier: Programming Language :: Python :: 3.9
Classifier: Programming Language :: Python :: 3.10
Classifier: Programming Language :: Python :: 3.11
Classifier: Programming Language :: Python :: 3.12
Classifier: Programming Language :: Python :: 3.13
Classifier: Programming Language :: Python :: 3.14
Classifier: Topic :: Scientific/Engineering :: Artificial Intelligence
Requires-Python: >3.7
License-File: LICENSE
License-File: LICENSE.header
Requires-Dist: lazy-imports
Requires-Dist: pyyaml
Requires-Dist: tomli; python_version < "3.11"
Requires-Dist: typing-extensions
Dynamic: license-file
